{"language": "en", "news": [{"title": "Rats, mould and dangerous overcrowding - inside illegal house-shares hiding in plain sight", "summary": "Black-market rental properties are being openly advertised with unsafe conditions, BBC finds.", "link": "https://www.bbc.com/news/articles/c04r7l455zeo?at_medium=RSS&at_campaign=rss", "source": "BBC News", "publication_date": "Fri, 01 Aug 2025 05:05:46 GMT"}, {"title": "Two girls shot in Gaza - BBC pieces together what happened and looks at dozens more child shootings", "summary": "Layan and Mira were killed in proximity to IDF soldiers - the Israeli military says intentional harm to civilians is prohibited and their cases will be examined by the authorities.", "link": "https://www.bbc.com/news/videos/cjelp738zd7o?at_medium=RSS&at_campaign=rss", "source": "BBC News", "publication_date": "Fri, 01 Aug 2025 05:07:20 GMT"}, {"title": "BBC faces mounting calls to pull MasterChef series", "summary": "It comes as a MasterChef contestant says she was edited out after asking for the new series not to be broadcast.", "link": "https://www.bbc.com/news/articles/cwye4840zdgo?at_medium=RSS&at_campaign=rss", "source": "BBC News", "publication_date": "Fri, 01 Aug 2025 07:31:34 GMT"}, {"title": "Storm Floris to bring 'unseasonably disruptive' rain and wind to UK", "summary": "UK Met Office has named Storm Floris which will bring strong winds and heavy rain on Monday.", "link": "https://www.bbc.com/weather/articles/cn47xd04x2xo?at_medium=RSS&at_campaign=rss", "source": "BBC News", "publication_date": "Fri, 01 Aug 2025 10:11:14 GMT"}, {"title": "Peaky Blinders creator will write new James Bond film", "summary": "Peaky Blinders writer Steven Knight tells the BBC writing Bond \"has always been on my bucket list\".", "link": "https://www.bbc.com/news/articles/c99mxlym3lko?at_medium=RSS&at_campaign=rss", "source": "BBC News", "publication_date": "Fri, 01 Aug 2025 09:27:34 GMT"}, {"title": "'Crazy' scenes at camp where children fell ill in suspected poisoning, locals say", "summary": "A 76-year-old man is under arrest after eight children who became unwell were taken to hospital.", "link": "https://www.bbc.com/news/articles/c8ryje8773go?at_medium=RSS&at_campaign=rss", "source": "BBC News", "publication_date": "Fri, 01 Aug 2025 10:49:11 GMT"}, {"title": "Civil service interns must be working class, government says", "summary": "Internships will only go to students from poorer families in a push to make Whitehall more working class.", "link": "https://www.bbc.com/news/articles/c3ez3v9v8jqo?at_medium=RSS&at_campaign=rss", "source": "BBC News", "publication_date": "Fri, 01 Aug 2025 10:08:47 GMT"}, {"title": "Stricter rules for older drivers could have saved my mum's life", "summary": "Claire Eady is calling for new regulations after losing her elderly mother in a crash.", "link": "https://www.bbc.com/news/articles/czell1g83nno?at_medium=RSS&at_campaign=rss", "source": "BBC News", "publication_date": "Fri, 01 Aug 2025 10:33:58 GMT"}, {"title": "Ten men arrested over child sex abuse in Bradford in 1990s", "summary": "The men, all from Bradford, are arrested in connection with child abuse offences dating back to 1994.", "link": "https://www.bbc.com/news/articles/c4glzyx8vyqo?at_medium=RSS&at_campaign=rss", "source": "BBC News", "publication_date": "Fri, 01 Aug 2025 10:04:38 GMT"}, {"title": "Shock, chaos and a hollow win: How Asian countries rushed to secure deals with Trump", "summary": "It's been a fraught process for many countries - with little detail about what exactly has been agreed.", "link": "https://www.bbc.com/news/articles/cger99z0yp9o?at_medium=RSS&at_campaign=rss", "source": "BBC News", "publication_date": "Fri, 01 Aug 2025 02:35:53 GMT"}]}