{"language": "en", "news": [{"title": "Top UN court says countries can sue each other over climate change", "summary": "The decision from the world's highest court has been welcomed by developing nations at most risk from climate change.", "link": "https://www.bbc.com/news/articles/ce379k4v3pwo", "source": "BBC News", "publication_date": "Wed, 23 Jul 2025 17:33:18 GMT"}, {"title": "Gazans 'wasting away' as mass starvation spreads, humanitarian groups warn", "summary": "A joint statement says aid workers are \"now joining the same food lines, risking being shot just to feed their families\".", "link": "https://www.bbc.com/news/articles/ce9xkx7vnmxo", "source": "BBC News", "publication_date": "Wed, 23 Jul 2025 14:40:44 GMT"}, {"title": "Mother and two children killed in Northern Ireland shooting, BBC understands", "summary": "Police say all three died from gunshot wounds and a man is seriously injured in hospital.", "link": "https://www.bbc.com/news/articles/cqx2537w5e2o", "source": "BBC News", "publication_date": "Wed, 23 Jul 2025 16:46:09 GMT"}, {"title": "Macrons file defamation suit against US influencer Candace Owens", "summary": "The French president and his wife say they have repeatedly asked for a retraction from the popular conspiracy theorist.", "link": "https://www.bbc.com/news/articles/c8739w8py4jo", "source": "BBC News", "publication_date": "Wed, 23 Jul 2025 16:53:16 GMT"}, {"title": "British surgeon who had his legs removed  accused of fraud", "summary": "Neil Hopper, 49, is also accused of encouraging the commission of grievous bodily harm.", "link": "https://www.bbc.com/news/articles/c75r21ww30vo", "source": "BBC News", "publication_date": "Wed, 23 Jul 2025 13:45:04 GMT"}, {"title": "Ozzy's fans flocked to Birmingham for his final gig. Now they are back to mourn him", "summary": "Makeshift shrines in the star's home city have pint glasses and whisky bottles among the flowers and candles.", "link": "https://www.bbc.com/news/articles/cd971z1g7wvo", "source": "BBC News", "publication_date": "Wed, 23 Jul 2025 17:04:10 GMT"}, {"title": "Police deny driving counter-protesters to asylum hotel demonstration", "summary": "Essex Police says it is not \"collaborating\" with people supporting asylum seekers in Epping.", "link": "https://www.bbc.com/news/articles/c4g8nzn3ne9o", "source": "BBC News", "publication_date": "Wed, 23 Jul 2025 14:19:23 GMT"}, {"title": "M&S ad banned over 'unhealthily thin' model", "summary": "The advertising watchdog said the model's pose and pointy shoes made her appear too slim.", "link": "https://www.bbc.com/news/articles/cly2j1322w9o", "source": "BBC News", "publication_date": "Wed, 23 Jul 2025 15:15:47 GMT"}, {"title": "City traders jailed for interest rate-rigging have convictions quashed", "summary": "Tom Hayes and Carlo Palombo said for a decade they were victims of a series of miscarriages of justice relating to the manipulation of Libor and Euribor interest rates.", "link": "https://www.bbc.com/news/articles/cr5vgqr8p14o", "source": "BBC News", "publication_date": "Wed, 23 Jul 2025 15:09:01 GMT"}, {"title": "Backlash grows after Zelensky strips anti-corruption bodies of independence", "summary": "Protests gather pace in Ukrainian cities as some of Kyiv's closest allies sound alarm bells.", "link": "https://www.bbc.com/news/articles/c9w19vxjr44o", "source": "BBC News", "publication_date": "Wed, 23 Jul 2025 17:07:29 GMT"}]}