{"language": "en", "news": [{"title": "Shudder to Think Announce First Tour Since 2008", "summary": "The D.C. hardcore veterans will play shows across the United States in October and November", "link": "https://pitchfork.com/news/shudder-to-think-announce-first-tour-since-2008", "source": "RSS: News", "publication_date": "Wed, 20 Aug 2025 03:31:49 +0000"}, {"title": "Paz Lenchantin Announces Debut Solo Album, Shares Video for New Song “Hang Tough”: Watch", "summary": "The Pixies alum will release Triste on October 17 via her own imprint, Hideous Human Records", "link": "https://pitchfork.com/news/paz-lenchantin-announces-debut-solo-album-shares-video-for-new-song-hang-tough-watch", "source": "RSS: News", "publication_date": "Wed, 20 Aug 2025 00:40:38 +0000"}]}